numcodecs_wasm_fourier_network/__init__.py
numcodecs_wasm_fourier_network/__init__.pyi
numcodecs_wasm_fourier_network/codec.wasm
numcodecs_wasm_fourier_network/py.typed
numcodecs_wasm_fourier_network-0.3.0.dist-info/METADATA
numcodecs_wasm_fourier_network-0.3.0.dist-info/WHEEL
numcodecs_wasm_fourier_network-0.3.0.dist-info/entry_points.txt
numcodecs_wasm_fourier_network-0.3.0.dist-info/top_level.txt
numcodecs_wasm_fourier_network-0.3.0.dist-info/RECORD
